{
  "version": 3,
  "middleware": {
    "/": {
      "files": [
        "server/edge-runtime-webpack.js",
        "server/src/middleware.js"
      ],
      "name": "src/middleware",
      "page": "/",
      "matchers": [
        {
          "regexp": "^(?:\\/(_next\\/data\\/[^/]{1,}))?\\/admin(?:\\/((?:[^\\/#\\?]+?)(?:\\/(?:[^\\/#\\?]+?))*))?(\\.json)?[\\/#\\?]?$",
          "originalSource": "/admin/:path*"
        }
      ],
      "wasm": [],
      "assets": [],
      "env": {
        "__NEXT_BUILD_ID": "34gBHujRja5rSWNpRpmAL",
        "NEXT_SERVER_ACTIONS_ENCRYPTION_KEY": "1Hj8svVg+FVh60MOWq+VDPfXfxQMGWg/44uK5UZglPQ=",
        "__NEXT_PREVIEW_MODE_ID": "efb7ee863e0ed98c2df32ebd3ef6c830",
        "__NEXT_PREVIEW_MODE_ENCRYPTION_KEY": "44f49344c7507f57a77a7559861d5ce20b2f76b8a283d9808c51a09184faa796",
        "__NEXT_PREVIEW_MODE_SIGNING_KEY": "128b37e9ec85066c7b26d179dca44ff53127f060778ead146f29639f8f22784e"
      }
    }
  },
  "functions": {},
  "sortedMiddleware": [
    "/"
  ]
}